crimson_agent/__init__.py
crimson_agent/agent.py
crimson_agent/social.py
crimson_agent/tools.py
crimson_agent-1.0.0.dist-info/LICENSE
crimson_agent-1.0.0.dist-info/METADATA
crimson_agent-1.0.0.dist-info/WHEEL
crimson_agent-1.0.0.dist-info/top_level.txt
crimson_agent-1.0.0.dist-info/RECORD
