Metadata-Version: 2.2
Name: crimson-agent
Version: 1.0.0
Summary: A Python package for creating science-themed AI agents with research and experimentation capabilities.
Home-page: https://github.com/crimson-labs/crimson-agent
Author: Crimson Labs
Author-email: crimsonlabsai@gmail.com
License: MIT
Project-URL: Documentation, https://github.com/crimson-labs/crimson-agent/tree/main/docs
Project-URL: Source, https://github.com/crimson-labs/crimson-agent
Project-URL: Issues, https://github.com/crimson-labs/crimson-agent/issues
Keywords: AI,OpenAI,science,research,agents,GPT,Crimson,DeSci,experiments,analysis,machine learning,data science,collaboration
Classifier: Development Status :: 3 - Alpha
Classifier: Intended Audience :: Developers
Classifier: Intended Audience :: Science/Research
Classifier: Intended Audience :: Education
Classifier: License :: OSI Approved :: MIT License
Classifier: Operating System :: OS Independent
Classifier: Programming Language :: Python :: 3
Classifier: Programming Language :: Python :: 3.8
Classifier: Programming Language :: Python :: 3.9
Classifier: Programming Language :: Python :: 3.10
Classifier: Programming Language :: Python :: 3.11
Classifier: Topic :: Scientific/Engineering
Classifier: Topic :: Scientific/Engineering :: Artificial Intelligence
Classifier: Topic :: Scientific/Engineering :: Information Analysis
Classifier: Topic :: Education
Classifier: Topic :: Software Development :: Libraries :: Python Modules
Requires-Python: >=3.8
License-File: LICENSE
Requires-Dist: openai>=0.28.0
Requires-Dist: asyncio
Requires-Dist: numpy>=1.21.0
Requires-Dist: scipy>=1.7.0
Requires-Dist: tweepy>=4.12.0
Requires-Dist: python-dateutil>=2.8.2
Requires-Dist: scikit-learn>=1.0.0
Requires-Dist: pandas>=1.3.0
Requires-Dist: matplotlib>=3.4.0
Requires-Dist: seaborn>=0.11.0
Requires-Dist: plotly>=5.3.0
Requires-Dist: PyPDF2>=3.0.0
Requires-Dist: arxiv>=1.4.0
Requires-Dist: networkx>=2.6.0
Requires-Dist: pyyaml>=6.0.0
Requires-Dist: gitpython>=3.1.0
Requires-Dist: nbformat>=5.7.0
Requires-Dist: markdown2>=2.4.0
Requires-Dist: jupyter>=1.0.0
Provides-Extra: dev
Requires-Dist: pytest>=7.0.0; extra == "dev"
Requires-Dist: pytest-cov>=3.0.0; extra == "dev"
Requires-Dist: black>=22.0.0; extra == "dev"
Requires-Dist: isort>=5.10.0; extra == "dev"
Requires-Dist: flake8>=4.0.0; extra == "dev"
Provides-Extra: ml
Requires-Dist: torch>=1.9.0; extra == "ml"
Requires-Dist: tensorflow>=2.6.0; extra == "ml"
Requires-Dist: xgboost>=1.5.0; extra == "ml"
Requires-Dist: lightgbm>=3.3.0; extra == "ml"
Provides-Extra: viz
Requires-Dist: bokeh>=2.4.0; extra == "viz"
Requires-Dist: altair>=4.2.0; extra == "viz"
Requires-Dist: plotly-express>=0.4.0; extra == "viz"
Provides-Extra: nlp
Requires-Dist: nltk>=3.6.0; extra == "nlp"
Requires-Dist: spacy>=3.2.0; extra == "nlp"
Requires-Dist: gensim>=4.1.0; extra == "nlp"
Dynamic: author
Dynamic: author-email
Dynamic: classifier
Dynamic: description
Dynamic: description-content-type
Dynamic: home-page
Dynamic: keywords
Dynamic: license
Dynamic: project-url
Dynamic: provides-extra
Dynamic: requires-dist
Dynamic: requires-python
Dynamic: summary
